[
    {
        "rank": 1,
        "title": "人魚の食卓",
        "user_name": "藤ちょこ（藤原）",
        "small_url": "https://i.pixiv.re/c/480x960/img-master/img/2026/02/28/00/00/10/141708029_p0_master1200.jpg",
        "page_url": "https://www.pixiv.net/artworks/141708029",
        "big_url": "https://www.pixiv.net/artworks/141708029",
        "tags": [
            "人魚",
            "オリジナル",
            "食卓",
            "ふつくしい",
            "腋",
            "オリジナル10000users入り",
            "金髪"
        ],
        "rating_count": 10313,
        "view_count": 76699
    },
    {
        "rank": 2,
        "title": "【創作】合コンに行ったら女がいなかった話７３",
        "user_name": "蒼川なな",
        "small_url": "https://i.pixiv.re/c/480x960/img-master/img/2026/02/27/00/00/18/141669558_p0_master1200.jpg",
        "page_url": "https://www.pixiv.net/artworks/141669558",
        "big_url": "https://www.pixiv.net/artworks/141669558",
        "tags": [
            "漫画",
            "男装",
            "合コンに行ったら女がいなかった話",
            "本命チョコ",
            "オリジナル30000users入り"
        ],
        "rating_count": 30904,
        "view_count": 291878
    },
    {
        "rank": 3,
        "title": "じいさんばあさん若返る【222】",
        "user_name": "新挑限",
        "small_url": "https://i.pixiv.re/c/480x960/img-master/img/2026/02/28/11/00/11/141723382_p0_master1200.jpg",
        "page_url": "https://www.pixiv.net/artworks/141723382",
        "big_url": "https://www.pixiv.net/artworks/141723382",
        "tags": [
            "漫画",
            "じいさんばあさん若返る",
            "結婚しよ",
            "老ックオン",
            "スナイ婆",
            "じいさんばあさん若返る外伝",
            "確固たる意思",
            "婆ニングラブ",
            "愛妻家",
            "オリジナル5000users入り"
        ],
        "rating_count": 7272,
        "view_count": 135939
    },
    {
        "rank": 4,
        "title": "個人メモ：シャツの襟",
        "user_name": "漫画素材工房",
        "small_url": "https://i.pixiv.re/c/480x960/img-master/img/2026/02/28/06/00/10/141717396_p0_master1200.jpg",
        "page_url": "https://www.pixiv.net/artworks/141717396",
        "big_url": "https://www.pixiv.net/artworks/141717396",
        "tags": [
            "漫画素材工房",
            "描き方",
            "身体",
            "人物",
            "服",
            "服のシワ",
            "シャツ",
            "シャツの襟"
        ],
        "rating_count": 1826,
        "view_count": 21767
    },
    {
        "rank": 5,
        "title": "新御三家",
        "user_name": "茉莉",
        "small_url": "https://i.pixiv.re/c/480x960/img-master/img/2026/02/28/11/43/32/141724358_p0_master1200.jpg",
        "page_url": "https://www.pixiv.net/artworks/141724358",
        "big_url": "https://www.pixiv.net/artworks/141724358",
        "tags": [
            "ポケモン",
            "ハブロウ",
            "ポムケン",
            "ミオリー",
            "ポケモン風波",
            "ポケットモンスター",
            "パートナーポケモン",
            "ポケモン1000users入り"
        ],
        "rating_count": 1605,
        "view_count": 16456
    },
    {
        "rank": 6,
        "title": "グレーターポムケン",
        "user_name": "SukeP（すけぴー）",
        "small_url": "https://i.pixiv.re/c/480x960/img-master/img/2026/02/28/15/20/54/141730047_p0_master1200.jpg",
        "page_url": "https://www.pixiv.net/artworks/141730047",
        "big_url": "https://www.pixiv.net/artworks/141730047",
        "tags": [
            "グレータードッグ",
            "ポムケン",
            "ポケモン",
            "ポケットモンスター",
            "GreaterDog",
            "ポケモン風波",
            "どうしてこうなった",
            "その発想はあった",
            "違和感が仕事しない"
        ],
        "rating_count": 1469,
        "view_count": 14755
    },
    {
        "rank": 7,
        "title": "♣️♥️♦️♠️",
        "user_name": "Rosuuri",
        "small_url": "https://i.pixiv.re/c/480x960/img-master/img/2026/02/27/00/09/00/141670377_p0_master1200.jpg",
        "page_url": "https://www.pixiv.net/artworks/141670377",
        "big_url": "https://www.pixiv.net/artworks/141670377",
        "tags": [
            "女の子",
            "オリジナル1000users入り",
            "金髪",
            "笑顔"
        ],
        "rating_count": 2830,
        "view_count": 19363
    },
    {
        "rank": 8,
        "title": "いびってこない義母と義姉  55話",
        "user_name": "おつじ",
        "small_url": "https://i.pixiv.re/c/480x960/img-master/img/2026/02/28/07/33/49/141719093_p0_master1200.jpg",
        "page_url": "https://www.pixiv.net/artworks/141719093",
        "big_url": "https://www.pixiv.net/artworks/141719093",
        "tags": [
            "漫画",
            "創作",
            "オリジナル",
            "いびってこない義母と義姉",
            "認証"
        ],
        "rating_count": 2365,
        "view_count": 73618
    },
    {
        "rank": 9,
        "title": "【会社と私生活】一緒でも",
        "user_name": "金沢真之介",
        "small_url": "https://i.pixiv.re/c/480x960/img-master/img/2026/02/27/12/00/29/141684047_p0_master1200.jpg",
        "page_url": "https://www.pixiv.net/artworks/141684047",
        "big_url": "https://www.pixiv.net/artworks/141684047",
        "tags": [
            "漫画",
            "会社と私生活",
            "なんで結婚してないんだよ",
            "オリジナル5000users入り"
        ],
        "rating_count": 5905,
        "view_count": 104058
    },
    {
        "rank": 10,
        "title": "私の魔法の先生は魔法が使えない（続）その58",
        "user_name": "あれっくす",
        "small_url": "https://i.pixiv.re/c/480x960/img-master/img/2026/02/28/00/01/07/141708305_p0_master1200.jpg",
        "page_url": "https://www.pixiv.net/artworks/141708305",
        "big_url": "https://www.pixiv.net/artworks/141708305",
        "tags": [
            "漫画",
            "四コマ",
            "私の魔法の先生は魔法が使えない",
            "オリジナル",
            "万物の用途は戦争にだって使える",
            "科学の発展と戦争は紙一重",
            "表裏一体",
            "技術者を異世界転移させたら恐ろしい例"
        ],
        "rating_count": 2101,
        "view_count": 53019
    },
    {
        "rank": 11,
        "title": "桜餅",
        "user_name": "チャイ",
        "small_url": "https://i.pixiv.re/c/480x960/img-master/img/2026/03/01/20/30/02/141786833_p0_master1200.jpg",
        "page_url": "https://www.pixiv.net/artworks/141786833",
        "big_url": "https://www.pixiv.net/artworks/141786833",
        "tags": [
            "オリジナル",
            "桜餅",
            "長命寺",
            "すいーつねこ",
            "あん(ね)こ",
            "脱皮",
            "香箱座り"
        ],
        "rating_count": 1817,
        "view_count": 18921
    },
    {
        "rank": 12,
        "title": "ポムケンに威嚇されたい",
        "user_name": "ヤシン/マンガ連載中",
        "small_url": "https://i.pixiv.re/c/480x960/img-master/img/2026/02/28/09/22/25/141721159_p0_master1200.jpg",
        "page_url": "https://www.pixiv.net/artworks/141721159",
        "big_url": "https://www.pixiv.net/artworks/141721159",
        "tags": [
            "ポケモン風波",
            "ポケモン",
            "ポムケン",
            "犬ポケモン",
            "ポケモン1000users入り"
        ],
        "rating_count": 1335,
        "view_count": 24433
    },
    {
        "rank": 13,
        "title": "肺",
        "user_name": "寺田てら",
        "small_url": "https://i.pixiv.re/c/480x960/img-master/img/2026/02/27/14/35/01/141687157_p0_master1200.jpg",
        "page_url": "https://www.pixiv.net/artworks/141687157",
        "big_url": "https://www.pixiv.net/artworks/141687157",
        "tags": [
            "肺",
            "lung"
        ],
        "rating_count": 1611,
        "view_count": 17439
    },
    {
        "rank": 14,
        "title": "「——石になれ」",
        "user_name": "ミナミ",
        "small_url": "https://i.pixiv.re/c/480x960/img-master/img/2026/02/28/18/38/26/141736356_p0_master1200.jpg",
        "page_url": "https://www.pixiv.net/artworks/141736356",
        "big_url": "https://www.pixiv.net/artworks/141736356",
        "tags": [
            "オリジナル",
            "メデューサ",
            "へび"
        ],
        "rating_count": 665,
        "view_count": 4154
    },
    {
        "rank": 15,
        "title": "転生したら碇シンジだったエヴァオタク15",
        "user_name": "おにくちゃん🔪肉斬り包丁",
        "small_url": "https://i.pixiv.re/c/480x960/img-master/img/2026/03/01/00/06/38/141752431_p0_master1200.jpg",
        "page_url": "https://www.pixiv.net/artworks/141752431",
        "big_url": "https://www.pixiv.net/artworks/141752431",
        "tags": [
            "漫画",
            "新世紀エヴァンゲリオン",
            "惣流・アスカ・ラングレー",
            "元彼vs今彼(予定)",
            "男の戦い",
            "山寺宏一"
        ],
        "rating_count": 2843,
        "view_count": 54842
    },
    {
        "rank": 16,
        "title": "ライチュウとポケ待機",
        "user_name": "カフェ",
        "small_url": "https://i.pixiv.re/c/480x960/img-master/img/2026/02/27/22/42/59/141704494_p0_master1200.jpg",
        "page_url": "https://www.pixiv.net/artworks/141704494",
        "big_url": "https://www.pixiv.net/artworks/141704494",
        "tags": [
            "ポケモン",
            "カフェライチュウ",
            "はもはも",
            "ライチュウも楽しそうですね",
            "どこ行くねーん!!",
            "なにこの仔かわいい",
            "謎の躍動感",
            "世界一平和なおいかけっこ",
            "偏るアンケート",
            "トレーナーさんにとっては割と死活問題"
        ],
        "rating_count": 1552,
        "view_count": 27445
    },
    {
        "rank": 17,
        "title": "メイド長と仲良くなりたい悪人顔王子",
        "user_name": "魔木",
        "small_url": "https://i.pixiv.re/c/480x960/img-master/img/2026/02/27/00/01/26/141669815_p0_master1200.jpg",
        "page_url": "https://www.pixiv.net/artworks/141669815",
        "big_url": "https://www.pixiv.net/artworks/141669815",
        "tags": [
            "漫画",
            "オリジナル",
            "オリジナル漫画",
            "創作漫画",
            "コメディ",
            "異世界",
            "勘違い",
            "丹精込めて作られた(真っ当な)お人形",
            "メアリー(目無し)",
            "人形遊び"
        ],
        "rating_count": 3303,
        "view_count": 72720
    },
    {
        "rank": 18,
        "title": "エミリア",
        "user_name": "雨壱絵穹",
        "small_url": "https://i.pixiv.re/c/480x960/img-master/img/2026/02/27/00/00/28/141669633_p0_master1200.jpg",
        "page_url": "https://www.pixiv.net/artworks/141669633",
        "big_url": "https://www.pixiv.net/artworks/141669633",
        "tags": [
            "エミリア",
            "リゼロ",
            "仕事絵",
            "リゼロ1000users入り",
            "笑顔",
            "キャップ"
        ],
        "rating_count": 1708,
        "view_count": 12767
    },
    {
        "rank": 19,
        "title": "クレアチンを飲みながら年齢を詐称してるVtuberの友人Vtub",
        "user_name": "なまず",
        "small_url": "https://i.pixiv.re/c/480x960/img-master/img/2026/02/28/21/11/13/141742940_p0_master1200.jpg",
        "page_url": "https://www.pixiv.net/artworks/141742940",
        "big_url": "https://www.pixiv.net/artworks/141742940",
        "tags": [
            "漫画",
            "バーチャルYouTuber",
            "VTuber",
            "星空バアド",
            "逆縞サバ",
            "反転術式",
            "超回復",
            "寝取られ漫画にクレアチン!",
            "お前らは何を言ってるんだ",
            "クレアチン「何それ知らん…怖…」"
        ],
        "rating_count": 1515,
        "view_count": 52084
    },
    {
        "rank": 20,
        "title": "猫にジェラるネコ🐈‍⬛",
        "user_name": "千種みのり@お仕事募集中",
        "small_url": "https://i.pixiv.re/c/480x960/img-master/img/2026/03/01/00/13/27/141752859_p0_master1200.jpg",
        "page_url": "https://www.pixiv.net/artworks/141752859",
        "big_url": "https://www.pixiv.net/artworks/141752859",
        "tags": [
            "オリジナル",
            "百合",
            "女の子",
            "着衣巨乳",
            "早乙女志乃",
            "白雪恋",
            "猫",
            "志乃と恋",
            "猫と女の子",
            "オリジナル5000users入り"
        ],
        "rating_count": 4873,
        "view_count": 78928
    },
    {
        "rank": 21,
        "title": "『The Frontline』",
        "user_name": "スコッティ",
        "small_url": "https://i.pixiv.re/c/480x960/img-master/img/2026/02/28/00/00/14/141708061_p0_master1200.jpg",
        "page_url": "https://www.pixiv.net/artworks/141708061",
        "big_url": "https://www.pixiv.net/artworks/141708061",
        "tags": [
            "Saruei",
            "バーチャルYouTuber1000users入り",
            "バーチャルYouTuber",
            "武器娘"
        ],
        "rating_count": 3127,
        "view_count": 30249
    },
    {
        "rank": 22,
        "title": "おいでよ　魔法少女村（不法占拠）84",
        "user_name": "ギンガム",
        "small_url": "https://i.pixiv.re/c/480x960/img-master/img/2026/02/28/10/45/13/141723051_p0_master1200.jpg",
        "page_url": "https://www.pixiv.net/artworks/141723051",
        "big_url": "https://www.pixiv.net/artworks/141723051",
        "tags": [
            "漫画",
            "オリジナル",
            "4コマ",
            "おいでよ_魔法少女村(不法占拠)",
            "ギンガム(漫画家)",
            "歩道が広いではないか…行け",
            "おでんパン",
            "桜子(魔法少女村)"
        ],
        "rating_count": 1478,
        "view_count": 45116
    },
    {
        "rank": 23,
        "title": "レインボーシックスモバイル",
        "user_name": "村カルキ",
        "small_url": "https://i.pixiv.re/c/480x960/img-master/img/2026/02/28/00/00/20/141708108_p0_master1200.jpg",
        "page_url": "https://www.pixiv.net/artworks/141708108",
        "big_url": "https://www.pixiv.net/artworks/141708108",
        "tags": [
            "レインボーシックスモバイル",
            "仕事絵"
        ],
        "rating_count": 590,
        "view_count": 6792
    },
    {
        "rank": 24,
        "title": "雑 + ミュルホル",
        "user_name": "uof",
        "small_url": "https://i.pixiv.re/c/480x960/img-master/img/2026/02/27/22/11/34/141703088_p0_master1200.jpg",
        "page_url": "https://www.pixiv.net/artworks/141703088",
        "big_url": "https://www.pixiv.net/artworks/141703088",
        "tags": [
            "アークナイツ",
            "明日方舟",
            "百合",
            "ホルハイヤ(アークナイツ)",
            "ミュルジス(アークナイツ)",
            "ミュルホル",
            "ペリカ(エンドフィールド)",
            "イヴォンヌ(エンドフィールド)",
            "ヴィヴィアナ(アークナイツ)"
        ],
        "rating_count": 1562,
        "view_count": 11168
    },
    {
        "rank": 25,
        "title": "魔王vs愛のパワー。",
        "user_name": "カコミスル",
        "small_url": "https://i.pixiv.re/c/480x960/img-master/img/2026/02/28/18/25/19/141735534_p0_master1200.jpg",
        "page_url": "https://www.pixiv.net/artworks/141735534",
        "big_url": "https://www.pixiv.net/artworks/141735534",
        "tags": [
            "漫画",
            "魔王",
            "カコミスルが好きなやつシリーズ",
            "年の差",
            "石破ラブラブ天驚拳",
            "愛の力",
            "木原マサキ",
            "痛恨の一撃",
            "勇者と魔王",
            "5コマ"
        ],
        "rating_count": 1701,
        "view_count": 45904
    },
    {
        "rank": 26,
        "title": "🎠",
        "user_name": "霖晴Phosphorus",
        "small_url": "https://i.pixiv.re/c/480x960/img-master/img/2026/02/28/18/39/58/141736400_p0_master1200.jpg",
        "page_url": "https://www.pixiv.net/artworks/141736400",
        "big_url": "https://www.pixiv.net/artworks/141736400",
        "tags": [
            "イラスト",
            "女の子",
            "commission",
            "仕事絵",
            "委托",
            "オリジナル",
            "遊園地",
            "メリーゴーランド",
            "回転木馬"
        ],
        "rating_count": 606,
        "view_count": 3273
    },
    {
        "rank": 27,
        "title": "新御三家！",
        "user_name": "ばん",
        "small_url": "https://i.pixiv.re/c/480x960/img-master/img/2026/02/28/00/16/56/141709361_p0_master1200.jpg",
        "page_url": "https://www.pixiv.net/artworks/141709361",
        "big_url": "https://www.pixiv.net/artworks/141709361",
        "tags": [
            "ポケモン",
            "ポケモン風波",
            "ポムケン",
            "ハブロウ",
            "ミオリー",
            "パートナーポケモン"
        ],
        "rating_count": 587,
        "view_count": 6547
    },
    {
        "rank": 28,
        "title": "ちびしの　其ノ肆",
        "user_name": "園れもん",
        "small_url": "https://i.pixiv.re/c/480x960/img-master/img/2026/02/28/11/05/10/141723529_p0_master1200.jpg",
        "page_url": "https://www.pixiv.net/artworks/141723529",
        "big_url": "https://www.pixiv.net/artworks/141723529",
        "tags": [
            "鬼滅の刃",
            "胡蝶しのぶ",
            "胡蝶カナエ",
            "ちびカエしの",
            "栗落花カナヲ",
            "鬼滅の刃500users入り"
        ],
        "rating_count": 616,
        "view_count": 7364
    },
    {
        "rank": 29,
        "title": "Choucroute garnie",
        "user_name": "純白可憐(Pale)",
        "small_url": "https://i.pixiv.re/c/480x960/img-master/img/2026/02/28/00/18/03/141709410_p0_master1200.jpg",
        "page_url": "https://www.pixiv.net/artworks/141709410",
        "big_url": "https://www.pixiv.net/artworks/141709410",
        "tags": [
            "オリジナル",
            "Sisi",
            "女の子"
        ],
        "rating_count": 1869,
        "view_count": 13305
    },
    {
        "rank": 30,
        "title": "30周年おめでとう！！",
        "user_name": "コソバ ユイ。",
        "small_url": "https://i.pixiv.re/c/480x960/img-master/img/2026/02/27/12/35/43/141684898_p0_master1200.jpg",
        "page_url": "https://www.pixiv.net/artworks/141684898",
        "big_url": "https://www.pixiv.net/artworks/141684898",
        "tags": [
            "ポケモン",
            "ポケットモンスター",
            "ポケモン30周年",
            "ポケギア",
            "ポケナビ"
        ],
        "rating_count": 1261,
        "view_count": 19305
    },
    {
        "rank": 31,
        "title": "想いを手紙に託して",
        "user_name": "のう",
        "small_url": "https://i.pixiv.re/c/480x960/img-master/img/2026/02/27/21/52/24/141701951_p0_master1200.jpg",
        "page_url": "https://www.pixiv.net/artworks/141701951",
        "big_url": "https://www.pixiv.net/artworks/141701951",
        "tags": [
            "東方LostWord",
            "射命丸文",
            "ラブレター(東方ロストワード)",
            "絵札(東方LW)",
            "東方"
        ],
        "rating_count": 1175,
        "view_count": 10996
    },
    {
        "rank": 32,
        "title": "【ポケモン30周年】タイプ：ワイルド",
        "user_name": "カフェ",
        "small_url": "https://i.pixiv.re/c/480x960/img-master/img/2026/02/27/00/06/14/141670225_master1200.jpg",
        "page_url": "https://www.pixiv.net/artworks/141670225",
        "big_url": "https://www.pixiv.net/artworks/141670225",
        "tags": [
            "うごイラ",
            "ポケモン",
            "カフェライチュウ",
            "ライチュウ",
            "オーキド",
            "タイプ:ワイルド",
            "なにこのおじじかわいい",
            "オーキド博士",
            "やっぱり偏るアンケート",
            "いつのまにか"
        ],
        "rating_count": 1255,
        "view_count": 20031
    },
    {
        "rank": 33,
        "title": "day230 辉夜想干什么😧",
        "user_name": "芸草冰",
        "small_url": "https://i.pixiv.re/c/480x960/img-master/img/2026/02/27/22/52/30/141704886_p0_master1200.jpg",
        "page_url": "https://www.pixiv.net/artworks/141704886",
        "big_url": "https://www.pixiv.net/artworks/141704886",
        "tags": [
            "超かぐや姫!",
            "酒寄彩葉",
            "かぐや",
            "超かぐや姫!1000users入り"
        ],
        "rating_count": 1614,
        "view_count": 17886
    },
    {
        "rank": 34,
        "title": "風波パートナー",
        "user_name": "マコトウ",
        "small_url": "https://i.pixiv.re/c/480x960/img-master/img/2026/02/28/01/30/39/141712202_p0_master1200.jpg",
        "page_url": "https://www.pixiv.net/artworks/141712202",
        "big_url": "https://www.pixiv.net/artworks/141712202",
        "tags": [
            "ポケモン",
            "ハブロウ",
            "ポムケン",
            "ミオリー",
            "ポケモン風波",
            "パートナーポケモン"
        ],
        "rating_count": 463,
        "view_count": 5504
    },
    {
        "rank": 35,
        "title": "【※元性別・ウマ息子・史実家族】スペクリザリエピ",
        "user_name": "はなつるヲ/skeb募集中",
        "small_url": "https://i.pixiv.re/c/480x960/img-master/img/2026/02/27/17/52/52/141691954_p0_master1200.jpg",
        "page_url": "https://www.pixiv.net/artworks/141691954",
        "big_url": "https://www.pixiv.net/artworks/141691954",
        "tags": [
            "ウマ娘プリティーダービー",
            "スペシャルウィーク(ウマ娘)",
            "シーザリオ(ウマ娘)",
            "シンボリクリスエス(ウマ娘)",
            "エピファネイア(ウマ娘)",
            "元性別化",
            "ウマ息子",
            "男体化",
            "クリザリ"
        ],
        "rating_count": 871,
        "view_count": 11771
    },
    {
        "rank": 36,
        "title": "レイス 🔍",
        "user_name": "ABP_ART",
        "small_url": "https://i.pixiv.re/c/480x960/img-master/img/2026/02/28/13/39/25/141727515_p0_master1200.jpg",
        "page_url": "https://www.pixiv.net/artworks/141727515",
        "big_url": "https://www.pixiv.net/artworks/141727515",
        "tags": [
            "ステラソラ",
            "StellaSora",
            "レイス(ステラソラ)",
            "極上の女体",
            "巨乳",
            "横乳",
            "巨尻",
            "揉みしだきたい乳",
            "腋",
            "スケベボディ"
        ],
        "rating_count": 3801,
        "view_count": 18902
    },
    {
        "rank": 37,
        "title": "纏　弐",
        "user_name": "AU",
        "small_url": "https://i.pixiv.re/c/480x960/img-master/img/2026/02/28/01/39/14/141712441_p0_master1200.jpg",
        "page_url": "https://www.pixiv.net/artworks/141712441",
        "big_url": "https://www.pixiv.net/artworks/141712441",
        "tags": [
            "刀剣乱舞",
            "三郎国宗(刀剣乱舞)",
            "三郎国宗",
            "本家",
            "刀剣乱舞1000users入り"
        ],
        "rating_count": 2683,
        "view_count": 23732
    },
    {
        "rank": 38,
        "title": "壁の花",
        "user_name": "べねぼれ",
        "small_url": "https://i.pixiv.re/c/480x960/img-master/img/2026/02/27/21/21/35/141700583_p0_master1200.jpg",
        "page_url": "https://www.pixiv.net/artworks/141700583",
        "big_url": "https://www.pixiv.net/artworks/141700583",
        "tags": [
            "百合",
            "オリジナル",
            "お嬢様",
            "メイド",
            "百合1000users入り",
            "オリジナル1000users入り"
        ],
        "rating_count": 1217,
        "view_count": 15471
    },
    {
        "rank": 39,
        "title": "Marching Princess",
        "user_name": "ねぎまぷりん",
        "small_url": "https://i.pixiv.re/c/480x960/img-master/img/2026/02/28/18/01/57/141734942_p0_master1200.jpg",
        "page_url": "https://www.pixiv.net/artworks/141734942",
        "big_url": "https://www.pixiv.net/artworks/141734942",
        "tags": [
            "オリジナル",
            "女の子",
            "少女",
            "創作",
            "ネコミミ",
            "猫耳",
            "オリジナル1000users入り"
        ],
        "rating_count": 1253,
        "view_count": 6434
    },
    {
        "rank": 40,
        "title": "新漫画版「エル薬」第17・18話更新のお知らせ",
        "user_name": "ぎばちゃん",
        "small_url": "https://i.pixiv.re/c/480x960/img-master/img/2026/02/27/18/15/09/141693067_p0_master1200.jpg",
        "page_url": "https://www.pixiv.net/artworks/141693067",
        "big_url": "https://www.pixiv.net/artworks/141693067",
        "tags": [
            "漫画",
            "オリジナル",
            "ボロボロのエルフさんを幸せにする薬売りさん",
            "エルフ",
            "リズレさん",
            "薬売りさん(エル薬)",
            "殺し屋",
            "エル薬",
            "誰かを助けるという事は、誰かを助けないという事。"
        ],
        "rating_count": 2138,
        "view_count": 59705
    },
    {
        "rank": 41,
        "title": "ポケモン30周年本当におめでとう！",
        "user_name": "温負 nullma",
        "small_url": "https://i.pixiv.re/c/480x960/img-master/img/2026/02/28/01/03/13/141711282_p0_master1200.jpg",
        "page_url": "https://www.pixiv.net/artworks/141711282",
        "big_url": "https://www.pixiv.net/artworks/141711282",
        "tags": [
            "ポケモン",
            "ポケモン風波",
            "ハブロウ",
            "ポムケン",
            "ミオリー",
            "パートナーポケモン",
            "ポケモン30周年"
        ],
        "rating_count": 431,
        "view_count": 3489
    },
    {
        "rank": 42,
        "title": "kaguya",
        "user_name": "さかな",
        "small_url": "https://i.pixiv.re/c/480x960/img-master/img/2026/02/27/23/18/29/141706130_p0_master1200.jpg",
        "page_url": "https://www.pixiv.net/artworks/141706130",
        "big_url": "https://www.pixiv.net/artworks/141706130",
        "tags": [
            "超かぐや姫!",
            "超かぐや姫",
            "酒寄彩葉",
            "かぐいろ",
            "かぐや(超かぐや姫!)",
            "百合"
        ],
        "rating_count": 1136,
        "view_count": 13200
    },
    {
        "rank": 43,
        "title": "絵の中の妖精",
        "user_name": "MAOH玥儿",
        "small_url": "https://i.pixiv.re/c/480x960/img-master/img/2026/02/27/00/02/17/141669920_p0_master1200.jpg",
        "page_url": "https://www.pixiv.net/artworks/141669920",
        "big_url": "https://www.pixiv.net/artworks/141669920",
        "tags": [
            "崩坏3rd",
            "崩壊3rd",
            "爱莉希雅",
            "エリシア(崩壊3rd)",
            "裸足",
            "足",
            "ピンク髪"
        ],
        "rating_count": 2192,
        "view_count": 9629
    },
    {
        "rank": 44,
        "title": "スぺつめ✿part12",
        "user_name": "yui_ko",
        "small_url": "https://i.pixiv.re/c/480x960/img-master/img/2026/02/28/10/43/25/141723017_p0_master1200.jpg",
        "page_url": "https://www.pixiv.net/artworks/141723017",
        "big_url": "https://www.pixiv.net/artworks/141723017",
        "tags": [
            "ポケスペ",
            "グリブル",
            "レイエ",
            "ゴークリ",
            "カントー組",
            "ポケスペ500users入り"
        ],
        "rating_count": 538,
        "view_count": 6770
    },
    {
        "rank": 45,
        "title": "멘헤라 디렉터",
        "user_name": "제육볶음",
        "small_url": "https://i.pixiv.re/c/480x960/img-master/img/2026/02/28/03/13/25/141714748_p0_master1200.jpg",
        "page_url": "https://www.pixiv.net/artworks/141714748",
        "big_url": "https://www.pixiv.net/artworks/141714748",
        "tags": [
            "Limbus_Company",
            "슈나쟝"
        ],
        "rating_count": 907,
        "view_count": 9958
    },
    {
        "rank": 46,
        "title": "【小春と湊】おっぱいサプライズ(中編)",
        "user_name": "ひあるろん&達磨",
        "small_url": "https://i.pixiv.re/c/480x960/img-master/img/2026/02/28/21/00/08/141742194_p0_master1200.jpg",
        "page_url": "https://www.pixiv.net/artworks/141742194",
        "big_url": "https://www.pixiv.net/artworks/141742194",
        "tags": [
            "オリジナル",
            "小春と湊",
            "エッセイ",
            "百合",
            "日常",
            "漫画",
            "LGBT",
            "GL",
            "FANBOX",
            "ビアン"
        ],
        "rating_count": 535,
        "view_count": 8015
    },
    {
        "rank": 47,
        "title": "エリクトリカルポム",
        "user_name": "辛口ムース",
        "small_url": "https://i.pixiv.re/c/480x960/img-master/img/2026/02/28/03/34/49/141715154_p0_master1200.jpg",
        "page_url": "https://www.pixiv.net/artworks/141715154",
        "big_url": "https://www.pixiv.net/artworks/141715154",
        "tags": [
            "ポケモン",
            "ポケモン風波",
            "ポムケン",
            "ゲーミングポムケン"
        ],
        "rating_count": 507,
        "view_count": 8078
    },
    {
        "rank": 48,
        "title": "１年で１ページだけ進むマンガの世界　8ページ目",
        "user_name": "ニ子(キドジロウ）",
        "small_url": "https://i.pixiv.re/c/480x960/img-master/img/2026/02/27/12/23/52/141684652_p0_master1200.jpg",
        "page_url": "https://www.pixiv.net/artworks/141684652",
        "big_url": "https://www.pixiv.net/artworks/141684652",
        "tags": [
            "漫画",
            "1年で1ページだけ進むマンガの世界",
            "お前が始めた物語だろ",
            "長期連載",
            "もう1年経ったとか嘘だろ嘘だって言ってくれよ",
            "恒例行事",
            "タグが病気",
            "逃がさない",
            "承認欲求モンスター"
        ],
        "rating_count": 1966,
        "view_count": 46845
    },
    {
        "rank": 49,
        "title": "バレンタイン🍫♥️",
        "user_name": "よもぎ꒰๑ ᷄ω ᷅꒱",
        "small_url": "https://i.pixiv.re/c/480x960/img-master/img/2026/02/28/10/55/53/141723273_p0_master1200.jpg",
        "page_url": "https://www.pixiv.net/artworks/141723273",
        "big_url": "https://www.pixiv.net/artworks/141723273",
        "tags": [
            "東方Project",
            "博麗霊夢",
            "霧雨魔理沙",
            "レイマリ"
        ],
        "rating_count": 449,
        "view_count": 2574
    },
    {
        "rank": 50,
        "title": "それは さり気ない告白＿＿＿＿",
        "user_name": "わがりろ",
        "small_url": "https://i.pixiv.re/c/480x960/img-master/img/2026/02/28/20/46/51/141741609_p0_master1200.jpg",
        "page_url": "https://www.pixiv.net/artworks/141741609",
        "big_url": "https://www.pixiv.net/artworks/141741609",
        "tags": [
            "超かぐや姫!",
            "かぐいろ",
            "百合",
            "超かぐや姫!1000users入り"
        ],
        "rating_count": 931,
        "view_count": 10555
    }
]