[
    {
        "rank": 1,
        "title": "エイメス",
        "user_name": "Hood",
        "small_url": "https://i.pixiv.re/c/480x960/img-master/img/2026/02/04/00/00/17/140739814_p0_master1200.jpg",
        "page_url": "https://www.pixiv.net/artworks/140739814",
        "big_url": "https://www.pixiv.net/artworks/140739814",
        "tags": [
            "鳴潮",
            "エイメス",
            "Aemeath",
            "WutheringWaves",
            "胸に手",
            "尻",
            "腕ブラ",
            "背中",
            "腋",
            "鳴潮10000users入り"
        ],
        "rating_count": 2864,
        "view_count": 49309
    },
    {
        "rank": 2,
        "title": "佩佩",
        "user_name": "千夜QYS3",
        "small_url": "https://i.pixiv.re/c/480x960/img-master/img/2026/02/04/00/22/52/140740430_p0_master1200.jpg",
        "page_url": "https://www.pixiv.net/artworks/140740430",
        "big_url": "https://www.pixiv.net/artworks/140740430",
        "tags": [
            "Arknights",
            "女の子",
            "佩丽卡",
            "アークナイツ:エンドフィールド",
            "ペリカ(エンドフィールド)",
            "エンドフィールド5000users入り",
            "背中",
            "オフショルダー",
            "手袋",
            "ジャケット"
        ],
        "rating_count": 2896,
        "view_count": 47231
    },
    {
        "rank": 3,
        "title": "リオ　「胸の上に置いて頂戴。アイスが溶けて合理的よ」（全7枚）",
        "user_name": "HOURAKU",
        "small_url": "https://i.pixiv.re/c/480x960/img-master/img/2026/02/04/20/00/45/140767039_p0_master1200.jpg",
        "page_url": "https://www.pixiv.net/artworks/140767039",
        "big_url": "https://www.pixiv.net/artworks/140767039",
        "tags": [
            "ブルーアーカイブ",
            "飛鳥馬トキ",
            "飛鳥馬トキ(臨戦)",
            "調月リオ",
            "調月リオ(臨戦)",
            "明星ヒマリ(臨戦)",
            "ブルアカ",
            "おっぱい",
            "ブルーアーカイブ5000users入り",
            "ボディスーツ"
        ],
        "rating_count": 1922,
        "view_count": 62880
    },
    {
        "rank": 4,
        "title": "キャラメルブレザータイツガール",
        "user_name": "天三月",
        "small_url": "https://i.pixiv.re/c/480x960/img-master/img/2026/02/04/19/52/42/140766617_p0_master1200.jpg",
        "page_url": "https://www.pixiv.net/artworks/140766617",
        "big_url": "https://www.pixiv.net/artworks/140766617",
        "tags": [
            "オリジナル",
            "女の子",
            "女子校生",
            "素足",
            "サンダル",
            "ビキニ",
            "背中",
            "黒スト",
            "ローファー",
            "尻"
        ],
        "rating_count": 1861,
        "view_count": 57548
    },
    {
        "rank": 5,
        "title": "モーニエ（健全）",
        "user_name": "MSK@水曜日東B05ab",
        "small_url": "https://i.pixiv.re/c/480x960/img-master/img/2026/02/04/20/30/09/140767116_p0_master1200.jpg",
        "page_url": "https://www.pixiv.net/artworks/140767116",
        "big_url": "https://www.pixiv.net/artworks/140767116",
        "tags": [
            "鳴潮",
            "モーニエ",
            "鳴潮5000users入り",
            "尻",
            "裸足",
            "片目隠れ",
            "ちっぱい",
            "照れ顔",
            "ビキニ",
            "白发"
        ],
        "rating_count": 1877,
        "view_count": 52007
    },
    {
        "rank": 6,
        "title": "🖤",
        "user_name": "Hinaki",
        "small_url": "https://i.pixiv.re/c/480x960/img-master/img/2026/02/04/00/00/11/140739770_p0_master1200.jpg",
        "page_url": "https://www.pixiv.net/artworks/140739770",
        "big_url": "https://www.pixiv.net/artworks/140739770",
        "tags": [
            "ベルベット(勝利の女神)",
            "NIKKE",
            "女の子",
            "魅惑の顔",
            "おっぱい",
            "巨乳",
            "魅惑のふともも",
            "汗",
            "バニーガール",
            "NIKKE5000users入り"
        ],
        "rating_count": 2324,
        "view_count": 27211
    },
    {
        "rank": 7,
        "title": "GLOOMY meets 初音ミク",
        "user_name": "LAM",
        "small_url": "https://i.pixiv.re/c/480x960/img-master/img/2026/02/04/00/00/21/140739848_p0_master1200.jpg",
        "page_url": "https://www.pixiv.net/artworks/140739848",
        "big_url": "https://www.pixiv.net/artworks/140739848",
        "tags": [
            "gloomybear",
            "グルーミー",
            "初音ミク",
            "VOCALOID",
            "VOCALOID5000users入り",
            "仕事絵"
        ],
        "rating_count": 1694,
        "view_count": 56330
    },
    {
        "rank": 8,
        "title": "映画館",
        "user_name": "逆流茶会",
        "small_url": "https://i.pixiv.re/c/480x960/img-master/img/2026/02/04/00/30/01/140741489_p0_master1200.jpg",
        "page_url": "https://www.pixiv.net/artworks/140741489",
        "big_url": "https://www.pixiv.net/artworks/140741489",
        "tags": [
            "女の子",
            "逆流茶会",
            "露出",
            "女子高生",
            "すじ",
            "睡眠",
            "ぱんつ",
            "ピンクパンツ",
            "パンチラ",
            "眠り"
        ],
        "rating_count": 2833,
        "view_count": 62093
    },
    {
        "rank": 9,
        "title": "デュイスブルク",
        "user_name": "くらしっく",
        "small_url": "https://i.pixiv.re/c/480x960/img-master/img/2026/02/04/22/00/17/140772481_p0_master1200.jpg",
        "page_url": "https://www.pixiv.net/artworks/140772481",
        "big_url": "https://www.pixiv.net/artworks/140772481",
        "tags": [
            "デュイスブルク(アズールレーン)",
            "アズールレーン",
            "デュイスブルク",
            "パンツ",
            "童貞を殺すセーター",
            "ぱんつ",
            "ボブ",
            "おっぱい",
            "おしり",
            "スケベボディ"
        ],
        "rating_count": 1583,
        "view_count": 23376
    },
    {
        "rank": 10,
        "title": "萊萬汀",
        "user_name": "儒宅",
        "small_url": "https://i.pixiv.re/c/480x960/img-master/img/2026/02/05/18/00/21/140800871_p0_master1200.jpg",
        "page_url": "https://www.pixiv.net/artworks/140800871",
        "big_url": "https://www.pixiv.net/artworks/140800871",
        "tags": [
            "Laevatain",
            "萊萬汀",
            "明日方舟終末地",
            "ArknightsEndfield",
            "アークナイツエンドフィールド",
            "莱万汀",
            "ぱんつ",
            "パンチラ",
            "アークナイツ:エンドフィールド",
            "エンドフィールド10000users入り"
        ],
        "rating_count": 2756,
        "view_count": 75944
    },
    {
        "rank": 11,
        "title": "Endmin",
        "user_name": "anon",
        "small_url": "https://i.pixiv.re/c/480x960/img-master/img/2026/02/02/22/06/23/140694427_p0_master1200.jpg",
        "page_url": "https://www.pixiv.net/artworks/140694427",
        "big_url": "https://www.pixiv.net/artworks/140694427",
        "tags": [
            "アークナイツ:エンドフィールド",
            "エンドフィールド",
            "ArknightsEndfield",
            "管理人(アークナイツエンドフィールド)",
            "管理人(エンドフィールド)",
            "女管理人",
            "目隠れ",
            "ピースサイン",
            "エンドフィールド10000users入り"
        ],
        "rating_count": 2611,
        "view_count": 69673
    },
    {
        "rank": 12,
        "title": "ジェーン・ドゥ",
        "user_name": "Xinとobiwan",
        "small_url": "https://i.pixiv.re/c/480x960/img-master/img/2026/02/04/19/06/32/140764929_p0_master1200.jpg",
        "page_url": "https://www.pixiv.net/artworks/140764929",
        "big_url": "https://www.pixiv.net/artworks/140764929",
        "tags": [
            "ジェーン・ドゥ",
            "ゼンレスゾーンゼロ",
            "ジェーン・ドゥ(ゼンゼロ)",
            "きらめくセレナーデ",
            "レオタード",
            "レオタードアンダーパンツ",
            "ねずみみ",
            "ゼンゼロ5000users入り",
            "黑髮",
            "尻尾"
        ],
        "rating_count": 1165,
        "view_count": 26331
    },
    {
        "rank": 13,
        "title": "サフェル",
        "user_name": "flasso",
        "small_url": "https://i.pixiv.re/c/480x960/img-master/img/2026/02/03/00/31/44/140701899_p0_master1200.jpg",
        "page_url": "https://www.pixiv.net/artworks/140701899",
        "big_url": "https://www.pixiv.net/artworks/140701899",
        "tags": [
            "崩壊:スターレイル",
            "崩壊スターレイル",
            "サフェル",
            "指でグイッ",
            "崩壊:スターレイル10000users入り"
        ],
        "rating_count": 3431,
        "view_count": 70162
    },
    {
        "rank": 14,
        "title": "無題",
        "user_name": "ひづるめ",
        "small_url": "https://i.pixiv.re/c/480x960/img-master/img/2026/02/04/00/00/18/140739819_p0_master1200.jpg",
        "page_url": "https://www.pixiv.net/artworks/140739819",
        "big_url": "https://www.pixiv.net/artworks/140739819",
        "tags": [
            "ゾアン・ファンイ",
            "アークナイツ:エンドフィールド",
            "おへそ",
            "ネギ",
            "エンドフィールド1000users入り"
        ],
        "rating_count": 1828,
        "view_count": 43176
    },
    {
        "rank": 15,
        "title": "アルザス",
        "user_name": "碳酸",
        "small_url": "https://i.pixiv.re/c/480x960/img-master/img/2026/02/04/19/00/07/140764550_p0_master1200.jpg",
        "page_url": "https://www.pixiv.net/artworks/140764550",
        "big_url": "https://www.pixiv.net/artworks/140764550",
        "tags": [
            "女の子",
            "巨乳",
            "魅惑の谷間",
            "アズールレーン",
            "極上の乳",
            "爆乳",
            "アルザス(アズールレーン)",
            "スケベボディ",
            "水着",
            "アズールレーン1000users入り"
        ],
        "rating_count": 936,
        "view_count": 17566
    },
    {
        "rank": 16,
        "title": "ケイちゃんと遊園地に行きたすぎるだろ！",
        "user_name": "ペケこ",
        "small_url": "https://i.pixiv.re/c/480x960/img-master/img/2026/02/04/00/00/20/140739838_p0_master1200.jpg",
        "page_url": "https://www.pixiv.net/artworks/140739838",
        "big_url": "https://www.pixiv.net/artworks/140739838",
        "tags": [
            "ブルーアーカイブ",
            "ブルアカ",
            "BlueArchive",
            "ケイ(ブルーアーカイブ)",
            "ペロロ",
            "照れ隠し",
            "ブルーアーカイブ1000users入り"
        ],
        "rating_count": 2029,
        "view_count": 56207
    },
    {
        "rank": 17,
        "title": "※ムリじゃなかった!?",
        "user_name": "leo-zero",
        "small_url": "https://i.pixiv.re/c/480x960/img-master/img/2026/02/04/13/16/12/140755970_p0_master1200.jpg",
        "page_url": "https://www.pixiv.net/artworks/140755970",
        "big_url": "https://www.pixiv.net/artworks/140755970",
        "tags": [
            "超かぐや姫!",
            "酒寄彩葉",
            "わたしが恋人になれるわけないじゃん、ムリムリ!",
            "月見ヤチヨ",
            "超かぐや姫!1000users入り",
            "かぐいろ"
        ],
        "rating_count": 303,
        "view_count": 25715
    },
    {
        "rank": 18,
        "title": "キュアアルカナ・シャドウ敗北",
        "user_name": "シチゴ",
        "small_url": "https://i.pixiv.re/c/480x960/img-master/img/2026/02/04/22/38/30/140774494_p0_master1200.jpg",
        "page_url": "https://www.pixiv.net/artworks/140774494",
        "big_url": "https://www.pixiv.net/artworks/140774494",
        "tags": [
            "名探偵プリキュア!",
            "キュアアルカナ・シャドウ",
            "敗北ヒロイン",
            "失神",
            "気絶",
            "ヒロピン",
            "ティアアルカナロッド",
            "たんプリ1000users入り",
            "黒キュア"
        ],
        "rating_count": 497,
        "view_count": 32438
    },
    {
        "rank": 19,
        "title": "Good Old Days",
        "user_name": "GaiNoob",
        "small_url": "https://i.pixiv.re/c/480x960/img-master/img/2026/02/04/02/28/00/140744919_p0_master1200.jpg",
        "page_url": "https://www.pixiv.net/artworks/140744919",
        "big_url": "https://www.pixiv.net/artworks/140744919",
        "tags": [
            "NIKKE",
            "勝利の女神:NIKKE",
            "ビーチボール",
            "ビキニ",
            "レッドフード(勝利の女神:NIKKE)",
            "汗",
            "お尻",
            "腿",
            "ピーチ",
            "赤髪"
        ],
        "rating_count": 306,
        "view_count": 16475
    },
    {
        "rank": 20,
        "title": "Bunny Firenze ~",
        "user_name": "ABP_ART",
        "small_url": "https://i.pixiv.re/c/480x960/img-master/img/2026/02/02/14/01/07/140677976_p0_master1200.jpg",
        "page_url": "https://www.pixiv.net/artworks/140677976",
        "big_url": "https://www.pixiv.net/artworks/140677976",
        "tags": [
            "StellaSora",
            "フィレン(ステラソラ)",
            "ステラソラ",
            "魅惑のふともも",
            "極上の女体",
            "おっぱい",
            "バニーガール",
            "横乳",
            "巨尻",
            "スケベボディ"
        ],
        "rating_count": 2087,
        "view_count": 32326
    },
    {
        "rank": 21,
        "title": "zzz",
        "user_name": "Kimsomang",
        "small_url": "https://i.pixiv.re/c/480x960/img-master/img/2026/02/06/02/53/26/140822057_p0_master1200.jpg",
        "page_url": "https://www.pixiv.net/artworks/140822057",
        "big_url": "https://www.pixiv.net/artworks/140822057",
        "tags": [
            "ZenlessZoneZero",
            "ゼンレスゾーンゼロ",
            "zzzero",
            "青衣(ゼンゼロ)",
            "ゼンゼロ",
            "朱鳶",
            "绝区零",
            "ジェーン・ドゥ(ゼンゼロ)",
            "尻タワー",
            "ゼンゼロ10000users入り"
        ],
        "rating_count": 482,
        "view_count": 51061
    },
    {
        "rank": 22,
        "title": "Aemeath",
        "user_name": "anon",
        "small_url": "https://i.pixiv.re/c/480x960/img-master/img/2026/02/05/21/00/46/140808232_p0_master1200.jpg",
        "page_url": "https://www.pixiv.net/artworks/140808232",
        "big_url": "https://www.pixiv.net/artworks/140808232",
        "tags": [
            "鳴潮",
            "鸣潮",
            "WutheringWaves",
            "エイメス",
            "ピンク髪",
            "ロリ",
            "おやつ",
            "マカロン",
            "鳴潮5000users入り"
        ],
        "rating_count": 1741,
        "view_count": 43216
    },
    {
        "rank": 23,
        "title": "管理人ちゃん",
        "user_name": "タブヘッド",
        "small_url": "https://i.pixiv.re/c/480x960/img-master/img/2026/02/02/17/36/01/140682796_p0_master1200.jpg",
        "page_url": "https://www.pixiv.net/artworks/140682796",
        "big_url": "https://www.pixiv.net/artworks/140682796",
        "tags": [
            "管理人(エンドフィールド)",
            "明日方舟終末地",
            "ArknightsEndfield",
            "アークナイツ:エンドフィールド",
            "笑顔",
            "女管理人",
            "エンドフィールド5000users入り",
            "黑髮",
            "赤面",
            "がおー"
        ],
        "rating_count": 1658,
        "view_count": 51453
    },
    {
        "rank": 24,
        "title": "ラストライト",
        "user_name": "ひづるめ",
        "small_url": "https://i.pixiv.re/c/480x960/img-master/img/2026/02/03/00/00/20/140700010_p0_master1200.jpg",
        "page_url": "https://www.pixiv.net/artworks/140700010",
        "big_url": "https://www.pixiv.net/artworks/140700010",
        "tags": [
            "ラストライト(エンドフィールド)",
            "アークナイツ:エンドフィールド",
            "おへそ",
            "エンドフィールド5000users入り"
        ],
        "rating_count": 2225,
        "view_count": 35560
    },
    {
        "rank": 25,
        "title": "イヴォンヌ",
        "user_name": "flasso",
        "small_url": "https://i.pixiv.re/c/480x960/img-master/img/2026/02/05/06/20/05/140786886_p0_master1200.jpg",
        "page_url": "https://www.pixiv.net/artworks/140786886",
        "big_url": "https://www.pixiv.net/artworks/140786886",
        "tags": [
            "アークナイツ",
            "アークナイツ:エンドフィールド",
            "イヴォンヌ(エンドフィールド)",
            "たくしあげ",
            "エンドフィールド5000users入り"
        ],
        "rating_count": 2770,
        "view_count": 67624
    },
    {
        "rank": 26,
        "title": "管理人",
        "user_name": "ひづるめ",
        "small_url": "https://i.pixiv.re/c/480x960/img-master/img/2026/02/06/00/00/13/140816621_p0_master1200.jpg",
        "page_url": "https://www.pixiv.net/artworks/140816621",
        "big_url": "https://www.pixiv.net/artworks/140816621",
        "tags": [
            "アークナイツ:エンドフィールド",
            "管理人(エンドフィールド)",
            "黒髪",
            "黒タイツ",
            "美脚",
            "黒スト",
            "エンドフィールド10000users入り",
            "女管理人"
        ],
        "rating_count": 3337,
        "view_count": 47645
    },
    {
        "rank": 27,
        "title": "Rio",
        "user_name": "Shigure@FANBOX",
        "small_url": "https://i.pixiv.re/c/480x960/img-master/img/2026/02/05/00/34/27/140780263_p0_master1200.jpg",
        "page_url": "https://www.pixiv.net/artworks/140780263",
        "big_url": "https://www.pixiv.net/artworks/140780263",
        "tags": [
            "ブルーアーカイブ",
            "BlueArchive",
            "ブルアカ",
            "調月リオ",
            "調月リオ(臨戦)",
            "谷間ホール",
            "巨乳",
            "クールビューティー",
            "鋼鉄大陸攻略戦"
        ],
        "rating_count": 2906,
        "view_count": 37057
    },
    {
        "rank": 28,
        "title": "ロジカルじゃない引退後",
        "user_name": "Takiki",
        "small_url": "https://i.pixiv.re/c/480x960/img-master/img/2026/02/04/14/57/32/140757898_p0_master1200.jpg",
        "page_url": "https://www.pixiv.net/artworks/140757898",
        "big_url": "https://www.pixiv.net/artworks/140757898",
        "tags": [
            "漫画",
            "ウマ娘プリティーダービー",
            "ウマ娘",
            "ファインモーション(ウマ娘)",
            "エアシャカール(ウマ娘)",
            "ウマ娘のその後",
            "トレシャカ",
            "ウマママ"
        ],
        "rating_count": 2197,
        "view_count": 104147
    },
    {
        "rank": 29,
        "title": "庄方宜大pp",
        "user_name": "阿戈魔AGM",
        "small_url": "https://i.pixiv.re/c/480x960/img-master/img/2026/02/05/12/44/37/140793804_p0_master1200.jpg",
        "page_url": "https://www.pixiv.net/artworks/140793804",
        "big_url": "https://www.pixiv.net/artworks/140793804",
        "tags": [
            "明日方舟",
            "尻神様",
            "臀部",
            "明日方舟:终末地",
            "庄方宜",
            "エンドフィールド5000users入り",
            "尻尾",
            "裏乳",
            "竜娘",
            "背中"
        ],
        "rating_count": 2748,
        "view_count": 67561
    },
    {
        "rank": 30,
        "title": "ぼだっこ",
        "user_name": "チャイ",
        "small_url": "https://i.pixiv.re/c/480x960/img-master/img/2026/02/04/20/30/01/140768290_p0_master1200.jpg",
        "page_url": "https://www.pixiv.net/artworks/140768290",
        "big_url": "https://www.pixiv.net/artworks/140768290",
        "tags": [
            "オリジナル",
            "ぼにゃっこ",
            "ぼだっこ",
            "塩鮭",
            "素晴らしきほっこりの世界",
            "イラストはほっこり、一欠片の塩分にびっくり",
            "ご飯泥棒",
            "いきものごはん",
            "食べ物1000users入り",
            "オリジナル1000users入り"
        ],
        "rating_count": 855,
        "view_count": 35925
    },
    {
        "rank": 31,
        "title": "うぅ…ケイちゃん…5周年コスして……",
        "user_name": "超ジロー🔞",
        "small_url": "https://i.pixiv.re/c/480x960/img-master/img/2026/02/06/21/00/11/140846474_p0_master1200.jpg",
        "page_url": "https://www.pixiv.net/artworks/140846474",
        "big_url": "https://www.pixiv.net/artworks/140846474",
        "tags": [
            "ブルアカ",
            "ケイ(ブルーアーカイブ)",
            "ブルーアーカイブ",
            "先生(ブルーアーカイブ)",
            "天童ケイ"
        ],
        "rating_count": 2140,
        "view_count": 100733
    },
    {
        "rank": 32,
        "title": "Coronis",
        "user_name": "rororo",
        "small_url": "https://i.pixiv.re/c/480x960/img-master/img/2026/02/03/18/05/50/140723642_p0_master1200.jpg",
        "page_url": "https://www.pixiv.net/artworks/140723642",
        "big_url": "https://www.pixiv.net/artworks/140723642",
        "tags": [
            "クルニス(ステラソラ)",
            "ステラソラ",
            "クルニス(華服)",
            "チャイナドレス",
            "ステラソラ1000users入り",
            "腋",
            "片目隠れ",
            "白ニーソックス",
            "ナース",
            "横乳"
        ],
        "rating_count": 1184,
        "view_count": 33408
    },
    {
        "rank": 33,
        "title": "day218 不是你想的那样😢",
        "user_name": "芸草冰",
        "small_url": "https://i.pixiv.re/c/480x960/img-master/img/2026/02/06/20/23/50/140844828_p0_master1200.jpg",
        "page_url": "https://www.pixiv.net/artworks/140844828",
        "big_url": "https://www.pixiv.net/artworks/140844828",
        "tags": [
            "超かぐや姫!",
            "酒寄彩葉",
            "かぐや",
            "かぐいろ",
            "月見ヤチヨ",
            "百合",
            "見つかった",
            "プリキュア寝取られミーム",
            "超かぐや姫!5000users入り",
            "超かぐや姫!10000users入り"
        ],
        "rating_count": 1233,
        "view_count": 85047
    },
    {
        "rank": 34,
        "title": "エイメス",
        "user_name": "ひづるめ",
        "small_url": "https://i.pixiv.re/c/480x960/img-master/img/2026/02/06/07/30/02/140826220_p0_master1200.jpg",
        "page_url": "https://www.pixiv.net/artworks/140826220",
        "big_url": "https://www.pixiv.net/artworks/140826220",
        "tags": [
            "鳴潮",
            "WutheringWaves",
            "エイメス",
            "背中",
            "鳴潮5000users入り",
            "見返り美人",
            "お尻"
        ],
        "rating_count": 2607,
        "view_count": 49465
    },
    {
        "rank": 35,
        "title": "【腐】安コ101",
        "user_name": "アキヲ",
        "small_url": "https://i.pixiv.re/c/480x960/img-master/img/2026/02/04/19/44/45/140765235_p0_master1200.jpg",
        "page_url": "https://www.pixiv.net/artworks/140765235",
        "big_url": "https://www.pixiv.net/artworks/140765235",
        "tags": [
            "漫画",
            "腐向け",
            "安コ",
            "降コ",
            "バボコ",
            "死体は喋らないでくださーい",
            "まじコナ腐5000users入り"
        ],
        "rating_count": 1325,
        "view_count": 69628
    },
    {
        "rank": 36,
        "title": "アクシデント",
        "user_name": "MILKTEA",
        "small_url": "https://i.pixiv.re/c/480x960/img-master/img/2026/02/04/07/00/06/140749123_p0_master1200.jpg",
        "page_url": "https://www.pixiv.net/artworks/140749123",
        "big_url": "https://www.pixiv.net/artworks/140749123",
        "tags": [
            "百合",
            "超かぐや姫!",
            "酒寄彩葉",
            "かぐや",
            "かぐいろ",
            "超かぐや姫!1000users入り"
        ],
        "rating_count": 752,
        "view_count": 17075
    },
    {
        "rank": 37,
        "title": "Zzz~",
        "user_name": "藤蝶.",
        "small_url": "https://i.pixiv.re/c/480x960/img-master/img/2026/02/03/00/09/40/140700849_p0_master1200.jpg",
        "page_url": "https://www.pixiv.net/artworks/140700849",
        "big_url": "https://www.pixiv.net/artworks/140700849",
        "tags": [
            "アズールレーン",
            "極上の女体",
            "AzurLane",
            "碧蓝航线",
            "極上の乳",
            "狐耳",
            "信濃(アズールレーン)",
            "守岸人",
            "ショアキーパー",
            "鳴潮"
        ],
        "rating_count": 1230,
        "view_count": 25743
    },
    {
        "rank": 38,
        "title": "🖤",
        "user_name": "スカイ",
        "small_url": "https://i.pixiv.re/c/480x960/img-master/img/2026/02/02/20/55/44/140690655_p0_master1200.jpg",
        "page_url": "https://www.pixiv.net/artworks/140690655",
        "big_url": "https://www.pixiv.net/artworks/140690655",
        "tags": [
            "角楯カリン",
            "ブルーアーカイブ",
            "角楯カリン(制服)",
            "おっぱい",
            "巨乳",
            "着衣巨乳",
            "胸の谷間",
            "ふともも",
            "ブルアカ",
            "ブルーアーカイブ5000users入り"
        ],
        "rating_count": 1623,
        "view_count": 40538
    },
    {
        "rank": 39,
        "title": "フリーナ",
        "user_name": "SushiSpin",
        "small_url": "https://i.pixiv.re/c/480x960/img-master/img/2026/02/04/18/00/14/140762410_p0_master1200.jpg",
        "page_url": "https://www.pixiv.net/artworks/140762410",
        "big_url": "https://www.pixiv.net/artworks/140762410",
        "tags": [
            "女の子",
            "原神",
            "フリーナ(原神)",
            "頬杖",
            "脚線美",
            "原神1000users入り",
            "膝"
        ],
        "rating_count": 605,
        "view_count": 16632
    },
    {
        "rank": 40,
        "title": "2/4は不死(undying)の日！",
        "user_name": "妖夢くん",
        "small_url": "https://i.pixiv.re/c/480x960/img-master/img/2026/02/04/18/32/46/140763697_p0_master1200.jpg",
        "page_url": "https://www.pixiv.net/artworks/140763697",
        "big_url": "https://www.pixiv.net/artworks/140763697",
        "tags": [
            "東方",
            "東方Project",
            "東方project",
            "藤原妹紅",
            "Undertale",
            "アンダイン",
            "Undyne",
            "Undyne_the_Undying",
            "おはようむ",
            "スシのニオイがする。"
        ],
        "rating_count": 549,
        "view_count": 57425
    },
    {
        "rank": 41,
        "title": "Velvet",
        "user_name": "MSK@水曜日東B05ab",
        "small_url": "https://i.pixiv.re/c/480x960/img-master/img/2026/02/06/22/52/27/140852152_p0_master1200.jpg",
        "page_url": "https://www.pixiv.net/artworks/140852152",
        "big_url": "https://www.pixiv.net/artworks/140852152",
        "tags": [
            "ベルベット",
            "勝利の女神:NIKKE",
            "ベルベット(勝利の女神:NIKKE)",
            "爆乳",
            "ニップルタッセル",
            "ハートニプレス",
            "魅惑のふともも",
            "NIKKE5000users入り",
            "ピンク髪"
        ],
        "rating_count": 2911,
        "view_count": 49949
    },
    {
        "rank": 42,
        "title": "見せしめ",
        "user_name": "つくだに",
        "small_url": "https://i.pixiv.re/c/480x960/img-master/img/2026/02/04/20/01/50/140767163_p0_master1200.jpg",
        "page_url": "https://www.pixiv.net/artworks/140767163",
        "big_url": "https://www.pixiv.net/artworks/140767163",
        "tags": [
            "漫画",
            "創作BL",
            "執着攻め",
            "美形×平凡",
            "BL漫画",
            "ヤンデレ",
            "オメガバース",
            "BL"
        ],
        "rating_count": 734,
        "view_count": 84589
    },
    {
        "rank": 43,
        "title": "さむいけどあったかい。",
        "user_name": "RYO@わんわん",
        "small_url": "https://i.pixiv.re/c/480x960/img-master/img/2026/02/04/01/02/42/140742783_p0_master1200.jpg",
        "page_url": "https://www.pixiv.net/artworks/140742783",
        "big_url": "https://www.pixiv.net/artworks/140742783",
        "tags": [
            "オリジナル",
            "女の子",
            "ぱんつ",
            "ブラジャー",
            "せーたー",
            "ニーソ",
            "ふともも",
            "雪",
            "しゅきぃ……",
            "オフショルダー"
        ],
        "rating_count": 231,
        "view_count": 17617
    },
    {
        "rank": 44,
        "title": "兹白 \\ Zibai",
        "user_name": "helloimtea",
        "small_url": "https://i.pixiv.re/c/480x960/img-master/img/2026/02/04/04/01/47/140746566_p0_master1200.jpg",
        "page_url": "https://www.pixiv.net/artworks/140746566",
        "big_url": "https://www.pixiv.net/artworks/140746566",
        "tags": [
            "原神",
            "GenshinImpact",
            "Genshin",
            "原神1000users入り",
            "girl",
            "おっぱい",
            "兹白",
            "Zibai",
            "ポニーテール",
            "白发"
        ],
        "rating_count": 253,
        "view_count": 10916
    },
    {
        "rank": 45,
        "title": "ケイ　ねこ",
        "user_name": "zds@fanbox",
        "small_url": "https://i.pixiv.re/c/480x960/img-master/img/2026/02/03/20/17/33/140728656_p0_master1200.jpg",
        "page_url": "https://www.pixiv.net/artworks/140728656",
        "big_url": "https://www.pixiv.net/artworks/140728656",
        "tags": [
            "ブルーアーカイブ",
            "ブルアカ",
            "女の子",
            "ケイ",
            "ケイ(ブルーアーカイブ)",
            "天童ケイ",
            "猫と女の子",
            "白发",
            "へそ",
            "髪ブラ"
        ],
        "rating_count": 935,
        "view_count": 20981
    },
    {
        "rank": 46,
        "title": "0204",
        "user_name": "Okkimon",
        "small_url": "https://i.pixiv.re/c/480x960/img-master/img/2026/02/04/15/13/08/140758361_p0_master1200.jpg",
        "page_url": "https://www.pixiv.net/artworks/140758361",
        "big_url": "https://www.pixiv.net/artworks/140758361",
        "tags": [
            "ブルーアーカイブ",
            "ブルアカ",
            "陸八魔アル",
            "部屋",
            "スマートフォン",
            "BlueArchive",
            "ヘイロー(ブルーアーカイブ)"
        ],
        "rating_count": 307,
        "view_count": 10470
    },
    {
        "rank": 47,
        "title": "無題",
        "user_name": "や",
        "small_url": "https://i.pixiv.re/c/480x960/img-master/img/2026/02/04/14/43/59/140757675_p0_master1200.jpg",
        "page_url": "https://www.pixiv.net/artworks/140757675",
        "big_url": "https://www.pixiv.net/artworks/140757675",
        "tags": [
            "ROF-MAO",
            "不破湊",
            "バーチャルYouTuber5000users入り"
        ],
        "rating_count": 628,
        "view_count": 62912
    },
    {
        "rank": 48,
        "title": "day217 月见八千代🥰",
        "user_name": "芸草冰",
        "small_url": "https://i.pixiv.re/c/480x960/img-master/img/2026/02/06/12/47/16/140832001_p0_master1200.jpg",
        "page_url": "https://www.pixiv.net/artworks/140832001",
        "big_url": "https://www.pixiv.net/artworks/140832001",
        "tags": [
            "超かぐや姫!",
            "月見ヤチヨ",
            "超かぐや姫!5000users入り"
        ],
        "rating_count": 823,
        "view_count": 44528
    },
    {
        "rank": 49,
        "title": "宗旨替え",
        "user_name": "イトコ",
        "small_url": "https://i.pixiv.re/c/480x960/img-master/img/2026/02/02/22/52/30/140696660_p0_master1200.jpg",
        "page_url": "https://www.pixiv.net/artworks/140696660",
        "big_url": "https://www.pixiv.net/artworks/140696660",
        "tags": [
            "漫画",
            "劇的ビフォーアフター",
            "夫婦",
            "オリジナル5000users入り",
            "女魔法使い",
            "優しい世界",
            "創作男女5000users入り",
            "即オチ2コマ",
            "綺麗なイトコ",
            "オリジナル10000users入り"
        ],
        "rating_count": 3230,
        "view_count": 219157
    }
]