[
    {
        "rank": 1,
        "title": "小さくなったマスターシリーズ31",
        "user_name": "幸永",
        "small_url": "https://i.pixiv.re/c/240x480/img-master/img/2025/01/17/00/10/16/126285203_p0_master1200.jpg",
        "page_url": "https://www.pixiv.net/artworks/126285203",
        "big_url": "https://i.pixiv.re/img-original/img/2025/01/17/00/10/16/126285203_p0.jpg",
        "tags": [
            "ぐだ男",
            "幼児化",
            "ダイダロス(Fate)",
            "スペース・エレシュキガル",
            "謎の代行者C.I.E.L",
            "ロクサーヌ(Fate)",
            "薬売り",
            "クロスオーバー",
            "ターボババア(ダンダダン)",
            "Fate/GO5000users入り"
        ],
        "rating_count": 1465,
        "view_count": 67393
    },
    {
        "rank": 2,
        "title": "世界の終りとハードボイルド・ワンダーランド",
        "user_name": "紺屋鴉江",
        "small_url": "https://i.pixiv.re/c/240x480/img-master/img/2025/01/17/22/14/55/126310510_p0_master1200.jpg",
        "page_url": "https://www.pixiv.net/artworks/126310510",
        "big_url": "https://i.pixiv.re/img-original/img/2025/01/17/22/14/55/126310510_p0.jpg",
        "tags": [
            "女の子",
            "VOCALOID",
            "初音ミク",
            "初音未来",
            "クリック推奨",
            "雪華蓄音機ミク",
            "VOCALOID1000users入り",
            "VOCALOID5000users入り",
            "ふつくしい"
        ],
        "rating_count": 2204,
        "view_count": 15562
    },
    {
        "rank": 3,
        "title": "二階建てのクッキー工房",
        "user_name": "ポ～ン（出水ぽすか）",
        "small_url": "https://i.pixiv.re/c/240x480/img-master/img/2025/01/17/07/30/02/126292401_p0_master1200.jpg",
        "page_url": "https://www.pixiv.net/artworks/126292401",
        "big_url": "https://i.pixiv.re/img-original/img/2025/01/17/07/30/02/126292401_p0.jpg",
        "tags": [
            "創作",
            "オリジナル",
            "クッキー"
        ],
        "rating_count": 840,
        "view_count": 18858
    },
    {
        "rank": 4,
        "title": "【会社と私生活】いつも通り",
        "user_name": "金沢真之介",
        "small_url": "https://i.pixiv.re/c/240x480/img-master/img/2025/01/17/12/00/22/126296043_p0_master1200.jpg",
        "page_url": "https://www.pixiv.net/artworks/126296043",
        "big_url": "https://i.pixiv.re/img-original/img/2025/01/17/12/00/22/126296043_p0.jpg",
        "tags": [
            "漫画",
            "会社と私生活",
            "オンとオフ",
            "パンク",
            "ロリィタ"
        ],
        "rating_count": 1767,
        "view_count": 88031
    },
    {
        "rank": 5,
        "title": "ずっと緊張していたの",
        "user_name": "ふに・無9",
        "small_url": "https://i.pixiv.re/c/240x480/img-master/img/2025/01/18/19/33/58/126338307_p0_master1200.jpg",
        "page_url": "https://www.pixiv.net/artworks/126338307",
        "big_url": "https://i.pixiv.re/img-original/img/2025/01/18/19/33/58/126338307_p0.jpg",
        "tags": [
            "漫画",
            "オリジナル",
            "怪異さんと俺",
            "創作漫画",
            "ポスト",
            "オカルト",
            "文通",
            "怪異たらし",
            "そうくるか、怪異誑しめ!",
            "失礼だな、純粋だよ"
        ],
        "rating_count": 1972,
        "view_count": 29049
    },
    {
        "rank": 6,
        "title": "【スタレ】カフカの漫画",
        "user_name": "BirdHatter",
        "small_url": "https://i.pixiv.re/c/240x480/img-master/img/2025/01/17/23/27/51/126312969_p0_master1200.jpg",
        "page_url": "https://www.pixiv.net/artworks/126312969",
        "big_url": "https://i.pixiv.re/img-original/img/2025/01/17/23/27/51/126312969_p0.png",
        "tags": [
            "漫画",
            "崩壊スターレイル",
            "カフカ(スターレイル)",
            "崩壊:スターレイル1000users入り"
        ],
        "rating_count": 1516,
        "view_count": 41476
    },
    {
        "rank": 7,
        "title": "いびってこない義母と義姉 44話",
        "user_name": "おつじ",
        "small_url": "https://i.pixiv.re/c/240x480/img-master/img/2025/01/18/00/02/25/126314480_p0_master1200.jpg",
        "page_url": "https://www.pixiv.net/artworks/126314480",
        "big_url": "https://i.pixiv.re/img-original/img/2025/01/18/00/02/25/126314480_p0.jpg",
        "tags": [
            "漫画",
            "いびってこない義母と義姉"
        ],
        "rating_count": 2124,
        "view_count": 60354
    },
    {
        "rank": 8,
        "title": "焼きながら年齢を詐称してるVtuberと社畜お嬢様系Vtuber",
        "user_name": "なまず",
        "small_url": "https://i.pixiv.re/c/240x480/img-master/img/2025/01/17/20/04/50/126306050_p0_master1200.jpg",
        "page_url": "https://www.pixiv.net/artworks/126306050",
        "big_url": "https://i.pixiv.re/img-original/img/2025/01/17/20/04/50/126306050_p0.png",
        "tags": [
            "漫画",
            "バーチャルYouTuber",
            "VTuber",
            "星空バアド",
            "逆縞サバ",
            "噛んだらわかるじゃん!",
            "餌付け",
            "コッペパン",
            "うっかりさんとガレッド・デ・ロワ",
            "頭を横切る某ホラゲ"
        ],
        "rating_count": 824,
        "view_count": 55462
    },
    {
        "rank": 9,
        "title": "The Herta",
        "user_name": "ATDAN-",
        "small_url": "https://i.pixiv.re/c/240x480/img-master/img/2025/01/18/02/35/02/126317423_p0_master1200.jpg",
        "page_url": "https://www.pixiv.net/artworks/126317423",
        "big_url": "https://i.pixiv.re/img-original/img/2025/01/18/02/35/02/126317423_p0.png",
        "tags": [
            "崩壊:スターレイル",
            "マダム・ヘルタ",
            "ヘルタ",
            "ソックス足裏",
            "美脚",
            "崩壊:スターレイル10000users入り"
        ],
        "rating_count": 5251,
        "view_count": 32388
    },
    {
        "rank": 10,
        "title": "女仆",
        "user_name": "阿戈魔AGM",
        "small_url": "https://i.pixiv.re/c/240x480/img-master/img/2025/01/17/13/09/34/126297216_p0_master1200.jpg",
        "page_url": "https://www.pixiv.net/artworks/126297216",
        "big_url": "https://i.pixiv.re/img-original/img/2025/01/17/13/09/34/126297216_p0.jpg",
        "tags": [
            "女の子",
            "欧派",
            "ソックス足裏",
            "黑丝",
            "足指",
            "调月莉音",
            "蔚蓝档案",
            "BlueArchive/블루아카이브/蔚藍檔案/蔚蓝",
            "女仆",
            "黒タイツ足裏"
        ],
        "rating_count": 2066,
        "view_count": 34415
    },
    {
        "rank": 11,
        "title": "個人メモ：手首の構造・簡易図",
        "user_name": "漫画素材工房",
        "small_url": "https://i.pixiv.re/c/240x480/img-master/img/2025/01/18/06/00/09/126321310_p0_master1200.jpg",
        "page_url": "https://www.pixiv.net/artworks/126321310",
        "big_url": "https://i.pixiv.re/img-original/img/2025/01/18/06/00/09/126321310_p0.jpg",
        "tags": [
            "漫画素材工房",
            "描き方",
            "人体",
            "身体",
            "手",
            "手首"
        ],
        "rating_count": 653,
        "view_count": 10723
    },
    {
        "rank": 12,
        "title": "捕まる",
        "user_name": "かめぱすた",
        "small_url": "https://i.pixiv.re/c/240x480/img-master/img/2025/01/17/00/27/06/126285749_p0_master1200.jpg",
        "page_url": "https://www.pixiv.net/artworks/126285749",
        "big_url": "https://i.pixiv.re/img-original/img/2025/01/17/00/27/06/126285749_p0.jpg",
        "tags": [
            "東方",
            "東方Project",
            "霧雨魔理沙",
            "ふもふも",
            "東方Project1000users入り"
        ],
        "rating_count": 174,
        "view_count": 5516
    },
    {
        "rank": 13,
        "title": "1人でノリノリだった奥さん",
        "user_name": "ぎばちゃん",
        "small_url": "https://i.pixiv.re/c/240x480/img-master/img/2025/01/17/00/53/59/126284908_p0_master1200.jpg",
        "page_url": "https://www.pixiv.net/artworks/126284908",
        "big_url": "https://i.pixiv.re/img-original/img/2025/01/17/00/53/59/126284908_p0.jpg",
        "tags": [
            "漫画",
            "オリジナル",
            "創作",
            "お茶目な奥さんとの日常茶番事",
            "奥さん",
            "茶山沙穂",
            "キングゲイナー",
            "ゲイナーダンス",
            "何がとは言わないが凄い・・・",
            "サタデーナイトフィーバー"
        ],
        "rating_count": 359,
        "view_count": 63437
    },
    {
        "rank": 14,
        "title": "昼寝中の攻防",
        "user_name": "チャイ",
        "small_url": "https://i.pixiv.re/c/240x480/img-master/img/2025/01/17/20/30/02/126306754_p0_master1200.jpg",
        "page_url": "https://www.pixiv.net/artworks/126306754",
        "big_url": "https://i.pixiv.re/img-original/img/2025/01/17/20/30/02/126306754_p0.png",
        "tags": [
            "漫画",
            "オリジナル",
            "おしるこ",
            "すいーつねこ",
            "キャットファイト"
        ],
        "rating_count": 987,
        "view_count": 18535
    },
    {
        "rank": 15,
        "title": "2025",
        "user_name": "凪白みと",
        "small_url": "https://i.pixiv.re/c/240x480/img-master/img/2025/01/17/00/00/16/126284535_p0_master1200.jpg",
        "page_url": "https://www.pixiv.net/artworks/126284535",
        "big_url": "https://i.pixiv.re/img-original/img/2025/01/17/00/00/16/126284535_p0.png",
        "tags": [
            "オリジナル",
            "女の子",
            "白发"
        ],
        "rating_count": 429,
        "view_count": 18474
    },
    {
        "rank": 16,
        "title": "ポケモンのイラスト漫画まとめ",
        "user_name": "麦田このみ@お仕事募集中",
        "small_url": "https://i.pixiv.re/c/240x480/img-master/img/2025/01/17/00/02/33/126284838_p0_master1200.jpg",
        "page_url": "https://www.pixiv.net/artworks/126284838",
        "big_url": "https://i.pixiv.re/img-original/img/2025/01/17/00/02/33/126284838_p0.jpg",
        "tags": [
            "ポケモン",
            "ピカチュウ",
            "イーブイ",
            "ニャオハ",
            "ホゲータ",
            "シャリタツ",
            "何この可愛い生き物",
            "ティーカップピカチュウ",
            "しわしわピカチュウ"
        ],
        "rating_count": 143,
        "view_count": 7381
    },
    {
        "rank": 17,
        "title": "正実モブちゃん",
        "user_name": "ひづるめ(Hidzzz)",
        "small_url": "https://i.pixiv.re/c/240x480/img-master/img/2025/01/17/00/00/19/126284554_p0_master1200.jpg",
        "page_url": "https://www.pixiv.net/artworks/126284554",
        "big_url": "https://i.pixiv.re/img-original/img/2025/01/17/00/00/19/126284554_p0.jpg",
        "tags": [
            "ブルーアーカイブ",
            "正義実現委員会のモブ",
            "ブルアカ",
            "BlueArchive",
            "おへそ",
            "見下し",
            "ブルーアーカイブ5000users入り"
        ],
        "rating_count": 531,
        "view_count": 33522
    },
    {
        "rank": 18,
        "title": "「すごい技考えた」",
        "user_name": "えびぽ",
        "small_url": "https://i.pixiv.re/c/240x480/img-master/img/2025/01/18/21/25/37/126342186_p0_master1200.jpg",
        "page_url": "https://www.pixiv.net/artworks/126342186",
        "big_url": "https://i.pixiv.re/img-original/img/2025/01/18/21/25/37/126342186_p0.jpg",
        "tags": [
            "にじさんじ",
            "Oriens",
            "Dytica",
            "MECHATU-A",
            "バーチャルYouTuber1000users入り"
        ],
        "rating_count": 371,
        "view_count": 7847
    },
    {
        "rank": 19,
        "title": "良牙くんが娘溺泉に落ちちゃった世界線も見てみたい",
        "user_name": "浅月のりと",
        "small_url": "https://i.pixiv.re/c/240x480/img-master/img/2025/01/18/00/00/11/126314087_p0_master1200.jpg",
        "page_url": "https://www.pixiv.net/artworks/126314087",
        "big_url": "https://i.pixiv.re/img-original/img/2025/01/18/00/00/11/126314087_p0.jpg",
        "tags": [
            "らんま1/2",
            "女体化",
            "TSF",
            "性転換",
            "響良牙",
            "娘溺泉",
            "女良牙",
            "呪泉郷"
        ],
        "rating_count": 1019,
        "view_count": 18060
    },
    {
        "rank": 20,
        "title": "私の魔法の先生は魔法が使えない（続）その32",
        "user_name": "あれっくす",
        "small_url": "https://i.pixiv.re/c/240x480/img-master/img/2025/01/18/00/01/09/126314318_p0_master1200.jpg",
        "page_url": "https://www.pixiv.net/artworks/126314318",
        "big_url": "https://i.pixiv.re/img-original/img/2025/01/18/00/01/09/126314318_p0.jpg",
        "tags": [
            "漫画",
            "私の魔法の先生は魔法が使えない",
            "オリジナル",
            "修羅場は踊る、されど進まず",
            "なんで各地で同時に大災害起きてるんだろうね・・・",
            "元凶が若手を大切にしなかった事とは思うまい",
            "サムネホイホイ",
            "報連相の大切さが良くわかる漫画",
            "※嘘です",
            "因果応報"
        ],
        "rating_count": 1109,
        "view_count": 28974
    },
    {
        "rank": 21,
        "title": "買っちゃった年齢を詐称してるVtuber（冬コミ同人も委託開始）",
        "user_name": "なまず",
        "small_url": "https://i.pixiv.re/c/240x480/img-master/img/2025/01/18/21/09/17/126341622_p0_master1200.jpg",
        "page_url": "https://www.pixiv.net/artworks/126341622",
        "big_url": "https://i.pixiv.re/img-original/img/2025/01/18/21/09/17/126341622_p0.png",
        "tags": [
            "漫画",
            "バーチャルYouTuber",
            "VTuber",
            "星空バアド",
            "悔し泣き",
            "NintendoSwitch2",
            "もちのロン",
            "オリジナル1000users入り"
        ],
        "rating_count": 621,
        "view_count": 31658
    },
    {
        "rank": 22,
        "title": "マダム・ヘルタ",
        "user_name": "Qiandai以宇",
        "small_url": "https://i.pixiv.re/c/240x480/img-master/img/2025/01/18/00/00/06/126314051_p0_master1200.jpg",
        "page_url": "https://www.pixiv.net/artworks/126314051",
        "big_url": "https://i.pixiv.re/img-original/img/2025/01/18/00/00/06/126314051_p0.png",
        "tags": [
            "ヘルタ",
            "ヘルタ(スターレイル)",
            "黑塔",
            "崩壊スターレイル",
            "マダム・ヘルタ",
            "女の子",
            "ふともも",
            "リブ生地",
            "崩壊:スターレイル5000users入り"
        ],
        "rating_count": 3272,
        "view_count": 19258
    },
    {
        "rank": 23,
        "title": "巨大メリーさん。",
        "user_name": "カコミスル",
        "small_url": "https://i.pixiv.re/c/240x480/img-master/img/2025/01/17/00/01/03/126284698_p0_master1200.jpg",
        "page_url": "https://www.pixiv.net/artworks/126284698",
        "big_url": "https://i.pixiv.re/img-original/img/2025/01/17/00/01/03/126284698_p0.jpg",
        "tags": [
            "メリーさんシリーズ",
            "アリさんマークの引越社",
            "巨大化",
            "優しい世界",
            "UFOキャッチャー",
            "使徒襲来",
            "バケツプリン",
            "多様性",
            "デカ過ぎんだろ…"
        ],
        "rating_count": 171,
        "view_count": 33656
    },
    {
        "rank": 24,
        "title": "シッテムの箱の日常",
        "user_name": "L.H.B@FANBOX開設中",
        "small_url": "https://i.pixiv.re/c/240x480/img-master/img/2025/01/17/00/06/48/126285048_p0_master1200.jpg",
        "page_url": "https://www.pixiv.net/artworks/126285048",
        "big_url": "https://i.pixiv.re/img-original/img/2025/01/17/00/06/48/126285048_p0.jpg",
        "tags": [
            "ブルーアーカイブ",
            "アロナ(ブルーアーカイブ)",
            "ブルアカ",
            "プラナ(ブルーアーカイブ)",
            "くすぐり",
            "足裏",
            "BlueArchive",
            "マイクロビキニ",
            "裸足裏",
            "濡れ"
        ],
        "rating_count": 250,
        "view_count": 7379
    },
    {
        "rank": 25,
        "title": "【創作】王様たちはあの子に夢中②",
        "user_name": "星見SK",
        "small_url": "https://i.pixiv.re/c/240x480/img-master/img/2025/01/18/00/05/03/126314695_p0_master1200.jpg",
        "page_url": "https://www.pixiv.net/artworks/126314695",
        "big_url": "https://i.pixiv.re/img-original/img/2025/01/18/00/05/03/126314695_p0.jpg",
        "tags": [
            "漫画",
            "オリジナル",
            "創作男女",
            "創作"
        ],
        "rating_count": 1986,
        "view_count": 31355
    },
    {
        "rank": 26,
        "title": "マダムヘルタの身支度お手伝いさせて欲しい",
        "user_name": "とーます　FANBOX更新中",
        "small_url": "https://i.pixiv.re/c/240x480/img-master/img/2025/01/17/00/28/19/126285789_p0_master1200.jpg",
        "page_url": "https://www.pixiv.net/artworks/126285789",
        "big_url": "https://i.pixiv.re/img-original/img/2025/01/17/00/28/19/126285789_p0.jpg",
        "tags": [
            "ヘルタ(スターレイル)",
            "崩壊スターレイル",
            "崩坏星穹铁道",
            "マダム・ヘルタ",
            "HonkaiStarRail",
            "腋",
            "崩壊:スターレイル5000users入り",
            "巨乳化",
            "このおっぱいで魔女は納得でしょ"
        ],
        "rating_count": 539,
        "view_count": 17066
    },
    {
        "rank": 27,
        "title": "守護部隊。",
        "user_name": "カコミスル",
        "small_url": "https://i.pixiv.re/c/240x480/img-master/img/2025/01/18/06/14/33/126321520_p0_master1200.jpg",
        "page_url": "https://www.pixiv.net/artworks/126321520",
        "big_url": "https://i.pixiv.re/img-original/img/2025/01/18/06/14/33/126321520_p0.jpg",
        "tags": [
            "違和感",
            "俺が守護らねばならぬ",
            "本部以蔵",
            "努力の方向音痴",
            "護衛",
            "守護らねば",
            "ありがた迷惑",
            "モブ",
            "抑止力",
            "ブサ猫"
        ],
        "rating_count": 1331,
        "view_count": 34426
    },
    {
        "rank": 28,
        "title": "ely eden mobi",
        "user_name": "DYA",
        "small_url": "https://i.pixiv.re/c/240x480/img-master/img/2025/01/17/07/14/33/126292179_p0_master1200.jpg",
        "page_url": "https://www.pixiv.net/artworks/126292179",
        "big_url": "https://i.pixiv.re/img-original/img/2025/01/17/07/14/33/126292179_p0.png",
        "tags": [
            "崩坏3rd",
            "崩壊3rd",
            "伊甸",
            "爱莉希雅",
            "梅比乌斯",
            "エデン",
            "エリシア",
            "メビウス",
            "百合"
        ],
        "rating_count": 132,
        "view_count": 3526
    },
    {
        "rank": 29,
        "title": "マスターが大好きなミクさん",
        "user_name": "アマネレイ",
        "small_url": "https://i.pixiv.re/c/240x480/img-master/img/2025/01/17/18/05/36/126302523_p0_master1200.jpg",
        "page_url": "https://www.pixiv.net/artworks/126302523",
        "big_url": "https://i.pixiv.re/img-original/img/2025/01/17/18/05/36/126302523_p0.jpg",
        "tags": [
            "初音ミク",
            "VOCALOID",
            "ボカロ",
            "VOCALOID500users入り"
        ],
        "rating_count": 144,
        "view_count": 8043
    },
    {
        "rank": 30,
        "title": "骨格ストレート",
        "user_name": "Toy(e)",
        "small_url": "https://i.pixiv.re/c/240x480/img-master/img/2025/01/17/07/04/28/126292047_p0_master1200.jpg",
        "page_url": "https://www.pixiv.net/artworks/126292047",
        "big_url": "https://i.pixiv.re/img-original/img/2025/01/17/07/04/28/126292047_p0.jpg",
        "tags": [
            "追弔禍征局",
            "オリジナル",
            "カーテン",
            "ドレス"
        ],
        "rating_count": 123,
        "view_count": 10650
    },
    {
        "rank": 31,
        "title": "【創作百合】高音さんと嵐ちゃん1P漫画まとめ106",
        "user_name": "なうち@単行本発売中",
        "small_url": "https://i.pixiv.re/c/240x480/img-master/img/2025/01/18/00/33/01/126314377_p0_master1200.jpg",
        "page_url": "https://www.pixiv.net/artworks/126314377",
        "big_url": "https://i.pixiv.re/img-original/img/2025/01/18/00/33/01/126314377_p0.jpg",
        "tags": [
            "漫画",
            "百合",
            "創作百合",
            "高音さんと嵐ちゃん",
            "オリジナル1000users入り",
            "百合1000users入り"
        ],
        "rating_count": 719,
        "view_count": 8781
    },
    {
        "rank": 32,
        "title": "Mococo's new outfit",
        "user_name": "Koahri",
        "small_url": "https://i.pixiv.re/c/240x480/img-master/img/2025/01/17/05/11/34/126290690_p0_master1200.jpg",
        "page_url": "https://www.pixiv.net/artworks/126290690",
        "big_url": "https://i.pixiv.re/img-original/img/2025/01/17/05/11/34/126290690_p0.png",
        "tags": [
            "バーチャルYouTuber",
            "HololiveEN",
            "ホロライブ",
            "holoAdvent",
            "mococo",
            "フワモコ",
            "FWMCpix",
            "モココ・アビスガード",
            "バーチャルYouTuber1000users入り"
        ],
        "rating_count": 381,
        "view_count": 8055
    },
    {
        "rank": 33,
        "title": "アスカガ",
        "user_name": "22",
        "small_url": "https://i.pixiv.re/c/240x480/img-master/img/2025/01/17/05/36/02/126290938_p0_master1200.jpg",
        "page_url": "https://www.pixiv.net/artworks/126290938",
        "big_url": "https://i.pixiv.re/img-original/img/2025/01/17/05/36/02/126290938_p0.png",
        "tags": [
            "漫画",
            "アスラン・ザラ",
            "機動戦士ガンダムSEEDFREEDOM",
            "カガリ・ユラ・アスハ",
            "アスカガ",
            "オリキャラ",
            "インフィニットジャスティスガンダム弐式",
            "リア充末永く爆発しろ"
        ],
        "rating_count": 148,
        "view_count": 37165
    },
    {
        "rank": 34,
        "title": "シュタフェル詰め20。",
        "user_name": "P助",
        "small_url": "https://i.pixiv.re/c/240x480/img-master/img/2025/01/18/23/07/20/126345932_p0_master1200.jpg",
        "page_url": "https://www.pixiv.net/artworks/126345932",
        "big_url": "https://i.pixiv.re/img-original/img/2025/01/18/23/07/20/126345932_p0.png",
        "tags": [
            "シュタフェル"
        ],
        "rating_count": 186,
        "view_count": 5258
    },
    {
        "rank": 35,
        "title": "フランドール・スカーレット",
        "user_name": "咲崎さきｐ",
        "small_url": "https://i.pixiv.re/c/240x480/img-master/img/2025/01/18/00/00/29/126314184_p0_master1200.jpg",
        "page_url": "https://www.pixiv.net/artworks/126314184",
        "big_url": "https://i.pixiv.re/img-original/img/2025/01/18/00/00/29/126314184_p0.png",
        "tags": [
            "東方",
            "東方Project",
            "フランドール・スカーレット",
            "妹様マジ天使",
            "東方Project1000users入り",
            "東方御脚拝"
        ],
        "rating_count": 809,
        "view_count": 7874
    },
    {
        "rank": 36,
        "title": "ジークアクス",
        "user_name": "ケースワベ【K-SUWABE】",
        "small_url": "https://i.pixiv.re/c/240x480/img-master/img/2025/01/18/00/00/21/126314136_p0_master1200.jpg",
        "page_url": "https://www.pixiv.net/artworks/126314136",
        "big_url": "https://i.pixiv.re/img-original/img/2025/01/18/00/00/21/126314136_p0.jpg",
        "tags": [
            "ジークアクス",
            "GQuuuuuuX",
            "機動戦士GundamGQuuuuuuX",
            "主人公機",
            "君は生き延びることができるか?",
            "ヒートホーク",
            "山下いくと",
            "翔び出して行け宇宙の彼方",
            "ガンダム1000users入り",
            "gMS-Ω"
        ],
        "rating_count": 1851,
        "view_count": 23971
    },
    {
        "rank": 37,
        "title": "迷迷",
        "user_name": "千夜QYS3",
        "small_url": "https://i.pixiv.re/c/240x480/img-master/img/2025/01/17/01/05/18/126286865_p0_master1200.jpg",
        "page_url": "https://www.pixiv.net/artworks/126286865",
        "big_url": "https://i.pixiv.re/img-original/img/2025/01/17/01/05/18/126286865_p0.jpg",
        "tags": [
            "迷迷",
            "崩坏星穹铁道",
            "女の子",
            "崩壊スターレイル",
            "ミュリオン",
            "ケモノ",
            "崩壊:スターレイル1000users入り"
        ],
        "rating_count": 485,
        "view_count": 24698
    },
    {
        "rank": 38,
        "title": "宇宙人のかくしごと　その18",
        "user_name": "ハミタ",
        "small_url": "https://i.pixiv.re/c/240x480/img-master/img/2025/01/18/02/47/05/126318837_p0_master1200.jpg",
        "page_url": "https://www.pixiv.net/artworks/126318837",
        "big_url": "https://i.pixiv.re/img-original/img/2025/01/18/02/47/05/126318837_p0.png",
        "tags": [
            "漫画",
            "衝撃のラスト",
            "キャ",
            "相思相愛",
            "偽善のすすめ"
        ],
        "rating_count": 1271,
        "view_count": 27135
    },
    {
        "rank": 39,
        "title": "生意気なギャル姉を解らせる話　第一話",
        "user_name": "江垣沼",
        "small_url": "https://i.pixiv.re/c/240x480/img-master/img/2025/01/17/18/15/42/126302798_p0_master1200.jpg",
        "page_url": "https://www.pixiv.net/artworks/126302798",
        "big_url": "https://i.pixiv.re/img-original/img/2025/01/17/18/15/42/126302798_p0.jpg",
        "tags": [
            "漫画",
            "オリジナル",
            "お姉ちゃん",
            "き",
            "分からせ",
            "生意気なギャル姉を解らせる話"
        ],
        "rating_count": 826,
        "view_count": 33724
    },
    {
        "rank": 40,
        "title": "予想外。",
        "user_name": "カコミスル",
        "small_url": "https://i.pixiv.re/c/240x480/img-master/img/2025/01/17/20/19/32/126306464_p0_master1200.jpg",
        "page_url": "https://www.pixiv.net/artworks/126306464",
        "big_url": "https://i.pixiv.re/img-original/img/2025/01/17/20/19/32/126306464_p0.jpg",
        "tags": [
            "特殊能力",
            "竿役",
            "薄い本",
            "風評被害",
            "メタフィクション",
            "適任",
            "ウ=ス異本",
            "誰このおっさん"
        ],
        "rating_count": 625,
        "view_count": 31600
    },
    {
        "rank": 41,
        "title": "私ね、夢があるんだ……",
        "user_name": "MaidCode1023",
        "small_url": "https://i.pixiv.re/c/240x480/img-master/img/2025/01/17/12/43/17/126295446_p0_master1200.jpg",
        "page_url": "https://www.pixiv.net/artworks/126295446",
        "big_url": "https://i.pixiv.re/img-original/img/2025/01/17/12/43/17/126295446_p0.png",
        "tags": [
            "百合",
            "ハッピーシュガーライフ",
            "松坂さとう",
            "神戸しお",
            "さとしお",
            "おねロリ",
            "女の子",
            "少女",
            "GL"
        ],
        "rating_count": 138,
        "view_count": 1810
    },
    {
        "rank": 42,
        "title": "おかえり、瑞希",
        "user_name": "心魚",
        "small_url": "https://i.pixiv.re/c/240x480/img-master/img/2025/01/17/18/01/10/126302337_p0_master1200.jpg",
        "page_url": "https://www.pixiv.net/artworks/126302337",
        "big_url": "https://i.pixiv.re/img-original/img/2025/01/17/18/01/10/126302337_p0.png",
        "tags": [
            "暁山瑞希",
            "プロセカ",
            "25時、ナイトコードで。",
            "朝比奈まふゆ",
            "東雲絵名",
            "宵崎奏"
        ],
        "rating_count": 112,
        "view_count": 4360
    },
    {
        "rank": 43,
        "title": "猫猫",
        "user_name": "Hong",
        "small_url": "https://i.pixiv.re/c/240x480/img-master/img/2025/01/17/00/44/51/126286303_p0_master1200.jpg",
        "page_url": "https://www.pixiv.net/artworks/126286303",
        "big_url": "https://i.pixiv.re/img-original/img/2025/01/17/00/44/51/126286303_p0.jpg",
        "tags": [
            "薬屋のひとりごと",
            "猫猫",
            "魅惑の背中",
            "濡れ透け",
            "尻神様",
            "水も滴るいい女",
            "見返り美人",
            "吸い込まれそうな瞳",
            "悠木碧",
            "薬屋1000users入り"
        ],
        "rating_count": 422,
        "view_count": 16414
    },
    {
        "rank": 44,
        "title": "「マスターが入ってるならまだ私も入ってます！」",
        "user_name": "knms",
        "small_url": "https://i.pixiv.re/c/240x480/img-master/img/2025/01/17/00/36/21/126286068_p0_master1200.jpg",
        "page_url": "https://www.pixiv.net/artworks/126286068",
        "big_url": "https://i.pixiv.re/img-original/img/2025/01/17/00/36/21/126286068_p0.jpg",
        "tags": [
            "初音ミク",
            "VOCALOID",
            "ボーカロイド",
            "ボカロ",
            "miku",
            "HatsuneMiku",
            "ミク",
            "ぽっぴっぽー",
            "我慢大会",
            "こたつ"
        ],
        "rating_count": 239,
        "view_count": 54404
    },
    {
        "rank": 45,
        "title": "駐車場にご注意！",
        "user_name": "せかねこ",
        "small_url": "https://i.pixiv.re/c/240x480/img-master/img/2025/01/18/16/59/59/126333734_p0_master1200.jpg",
        "page_url": "https://www.pixiv.net/artworks/126333734",
        "big_url": "https://i.pixiv.re/img-original/img/2025/01/18/16/59/59/126333734_p0.png",
        "tags": [
            "漫画",
            "創作",
            "4コマ",
            "オリジナル"
        ],
        "rating_count": 766,
        "view_count": 12293
    },
    {
        "rank": 46,
        "title": "no title",
        "user_name": "飞机云君",
        "small_url": "https://i.pixiv.re/c/240x480/img-master/img/2025/01/17/20/28/57/126306720_p0_master1200.jpg",
        "page_url": "https://www.pixiv.net/artworks/126306720",
        "big_url": "https://i.pixiv.re/img-original/img/2025/01/17/20/28/57/126306720_p0.jpg",
        "tags": [
            "女の子",
            "美少女",
            "可愛い",
            "miku",
            "VOCALOID",
            "ミク",
            "初音",
            "初音ミク",
            "VOCALOID500users入り"
        ],
        "rating_count": 271,
        "view_count": 1681
    },
    {
        "rank": 47,
        "title": "Nunholy is on Steam!",
        "user_name": "Chowbie",
        "small_url": "https://i.pixiv.re/c/240x480/img-master/img/2025/01/18/00/00/34/126314215_p0_master1200.jpg",
        "page_url": "https://www.pixiv.net/artworks/126314215",
        "big_url": "https://i.pixiv.re/img-original/img/2025/01/18/00/00/34/126314215_p0.png",
        "tags": [
            "Nunholy",
            "シスター"
        ],
        "rating_count": 1823,
        "view_count": 12824
    },
    {
        "rank": 48,
        "title": "ルギア",
        "user_name": "SukeP（すけぴー）",
        "small_url": "https://i.pixiv.re/c/240x480/img-master/img/2025/01/19/00/45/45/126338333_p0_master1200.jpg",
        "page_url": "https://www.pixiv.net/artworks/126338333",
        "big_url": "https://i.pixiv.re/img-original/img/2025/01/19/00/45/45/126338333_p0.jpg",
        "tags": [
            "ルギア",
            "海",
            "ポケモン",
            "ポケットモンスター",
            "伝説ポケモン"
        ],
        "rating_count": 196,
        "view_count": 1960
    },
    {
        "rank": 49,
        "title": "ザ・ヘルタ",
        "user_name": "きなつｋ",
        "small_url": "https://i.pixiv.re/c/240x480/img-master/img/2025/01/17/21/04/29/126307981_p0_master1200.jpg",
        "page_url": "https://www.pixiv.net/artworks/126307981",
        "big_url": "https://i.pixiv.re/img-original/img/2025/01/17/21/04/29/126307981_p0.jpg",
        "tags": [
            "崩壊スターレイル",
            "HonkaiStarRail",
            "マダム・ヘルタ",
            "ヘルタ(スターレイル)",
            "崩壊:スターレイル500users入り"
        ],
        "rating_count": 261,
        "view_count": 3545
    },
    {
        "rank": 50,
        "title": "フォーミダブル",
        "user_name": "失楽园",
        "small_url": "https://i.pixiv.re/c/240x480/img-master/img/2025/01/17/14/48/35/126298664_p0_master1200.jpg",
        "page_url": "https://www.pixiv.net/artworks/126298664",
        "big_url": "https://i.pixiv.re/img-original/img/2025/01/17/14/48/35/126298664_p0.png",
        "tags": [
            "フォーミダブル(アズールレーン)",
            "白丝",
            "足裏",
            "撫で回したいお腹",
            "アズールレーン",
            "女の子",
            "AzurLane",
            "美脚",
            "アズールレーン1000users入り",
            "ソックス足裏"
        ],
        "rating_count": 649,
        "view_count": 7287
    }
]